ctadata/__init__.py
ctadata/api.py
ctadata/cli.py
ctadata-0.7.0.dist-info/METADATA
ctadata-0.7.0.dist-info/WHEEL
ctadata-0.7.0.dist-info/entry_points.txt
ctadata-0.7.0.dist-info/RECORD
