Metadata-Version: 2.3
Name: ctadata
Version: 0.7.0
Summary: 
Author: Volodymyr Savchenko
Author-email: contact@volodymyrsavchenko.com
Requires-Python: >=3.8,<4.0
Classifier: Programming Language :: Python :: 3
Classifier: Programming Language :: Python :: 3.8
Classifier: Programming Language :: Python :: 3.9
Classifier: Programming Language :: Python :: 3.10
Classifier: Programming Language :: Python :: 3.11
Classifier: Programming Language :: Python :: 3.12
Classifier: Programming Language :: Python :: 3.13
Requires-Dist: click (>=8.1.3,<9.0.0)
Requires-Dist: httpx (>=0.26.0,<0.27.0)
Requires-Dist: importlib-metadata (>=7.0.0,<8.0.0)
Requires-Dist: requests (>=2.31.0,<3.0.0)
Requires-Dist: webdav4 (>=0.9.8,<0.10.0)
